pysocha/__init__.py
pysocha/__main__.py
pysocha/atom.py
pysocha/build.py
pysocha/config.py
pysocha/markdown.py
pysocha/preview.py
pysocha-0.2.0.dist-info/METADATA
pysocha-0.2.0.dist-info/WHEEL
pysocha-0.2.0.dist-info/entry_points.txt
pysocha-0.2.0.dist-info/RECORD
